{"artist_era": {"2": {"TEXT": "Late 2000's", "ID": "29493"}, "1": {"TEXT": "2000's", "ID": "29483"}}, "tempo": {}, "artist_origin": {"2": {"TEXT": "United Kingdom", "ID": "29967"}, "4": {"TEXT": "Belfast", "ID": "30831"}, "3": {"TEXT": "Northern Ireland", "ID": "30314"}, "1": {"TEXT": "Western Europe", "ID": "29894"}}, "album_art_url": "http://akamai-b.cdn.cddbp.net/cds/2.0/cover/1F5B/3215/7BB4/153C_medium_front.jpg?cid=1247529661", "track_gnid": "", "review_url": "", "track_number": "", "artist_bio_url": "", "artist_type": {"2": {"TEXT": "Male Group", "ID": "29436"}, "1": {"TEXT": "Male", "ID": "29422"}}, "tracks": [{"tempo": {"2": {"TEXT": "Medium Fast", "ID": "34291"}, "3": {"TEXT": "110s", "ID": "34323"}, "1": {"TEXT": "Medium Tempo", "ID": "34283"}}, "mood": {"2": {"TEXT": "Heavy Triumphant", "ID": "43032"}, "1": {"TEXT": "Aggressive", "ID": "42958"}}, "track_title": "Beautifuluniversemasterchampion", "track_gnid": "240980633-0440087BB248C6D932BB38D2AB760D45", "track_number": "1", "track_artist_name": ""}, {"tempo": {"2": {"TEXT": "Very Fast", "ID": "34293"}, "3": {"TEXT": "250s", "ID": "34347"}, "1": {"TEXT": "Fast Tempo", "ID": "43078"}}, "mood": {"2": {"TEXT": "Heavy Triumphant", "ID": "43032"}, "1": {"TEXT": "Aggressive", "ID": "42958"}}, "track_title": "Gang (Starting Never Stopping)", "track_gnid": "240980634-539016C9D4C36D2A45C9557F3836618D", "track_number": "2", "track_artist_name": ""}, {"tempo": {"2": {"TEXT": "Medium", "ID": "34290"}, "3": {"TEXT": "70s", "ID": "34313"}, "1": {"TEXT": "Medium Tempo", "ID": "34283"}}, "mood": {"2": {"TEXT": "Heavy Triumphant", "ID": "43032"}, "1": {"TEXT": "Aggressive", "ID": "42958"}}, "track_title": "Search:Party:Animal", "track_gnid": "240980635-580F7A145EF266A4D0D91B7ECE0FEB39", "track_number": "3", "track_artist_name": ""}, {"tempo": {"2": {"TEXT": "Medium Slow", "ID": "34289"}, "3": {"TEXT": "60s", "ID": "34311"}, "1": {"TEXT": "Medium Tempo", "ID": "34283"}}, "mood": {"2": {"TEXT": "Dreamy Brooding", "ID": "43025"}, "1": {"TEXT": "Brooding", "ID": "65329"}}, "track_title": "7 Billion People All Alive At Once", "track_gnid": "240980636-85504B6FD6515E6A5AB4AF1427820658", "track_number": "4", "track_artist_name": ""}, {"tempo": {"2": {"TEXT": "Fast", "ID": "34292"}, "3": {"TEXT": "170s", "ID": "34333"}, "1": {"TEXT": "Fast Tempo", "ID": "43078"}}, "mood": {"2": {"TEXT": "Heavy Triumphant", "ID": "43032"}, "1": {"TEXT": "Aggressive", "ID": "42958"}}, "track_title": "Think:Breathe:Destroy", "track_gnid": "240980637-21EAAD9D3AE91ED208C0AA0BDBC3740A", "track_number": "5", "track_artist_name": ""}, {"tempo": {"2": {"TEXT": "Very Slow", "ID": "34287"}, "3": {"TEXT": "30s", "ID": "34300"}, "1": {"TEXT": "Slow Tempo", "ID": "34282"}}, "mood": {"2": {"TEXT": "Dreamy Pulse", "ID": "42993"}, "1": {"TEXT": "Sensual", "ID": "42947"}}, "track_title": "Homes - Ghost Parlor KA -6 To\u2026", "track_gnid": "240980638-7A00D820A9C2404B9601A91B2DDBF45F", "track_number": "6", "track_artist_name": ""}, {"tempo": {"2": {"TEXT": "Fast", "ID": "34292"}, "3": {"TEXT": "130s", "ID": "34537"}, "1": {"TEXT": "Fast Tempo", "ID": "43078"}}, "mood": {"2": {"TEXT": "Heavy Triumphant", "ID": "43032"}, "1": {"TEXT": "Aggressive", "ID": "42958"}}, "track_title": "Homes - ...Samara To Belfast", "track_gnid": "240980639-39A7446959B5FC94E240B18EFE26B549", "track_number": "7", "track_artist_name": ""}, {"tempo": {"2": {"TEXT": "Very Fast", "ID": "34293"}, "3": {"TEXT": "250s", "ID": "34347"}, "1": {"TEXT": "Fast Tempo", "ID": "43078"}}, "mood": {"2": {"TEXT": "Heavy Triumphant", "ID": "43032"}, "1": {"TEXT": "Aggressive", "ID": "42958"}}, "track_title": "Lifeproof", "track_gnid": "240980640-566E91E290266CDF8C9CDD3D276DB5A1", "track_number": "8", "track_artist_name": ""}], "track_artist_name": "", "album_artist_name": "... And So I Watch You From Afar", "artist_image_url": "", "mood": {}, "track_title": "", "album_gnid": "240980632-1AAE6F17D71C15A45B833627A41CB79D", "genre": {"2": {"TEXT": "Indie Rock", "ID": "35477"}, "3": {"TEXT": "Post-Rock", "ID": "25465"}, "1": {"TEXT": "Alternative & Punk", "ID": "25312"}}, "album_title": "Gangs", "album_year": "2011", "xid": "", "radio_id": ""}