{"track_title": "", "album_artist_name": "Clika One", "mood": {}, "artist_bio_url": "", "artist_image_url": "", "artist_era": {}, "album_year": "2012", "radio_id": "", "tempo": {}, "track_gnid": "", "track_number": "", "review_url": "", "album_art_url": "http://akamai-b.cdn.cddbp.net/cds/2.0/cover/C1CE/323D/6AF6/123D_medium_front.jpg?cid=1247529661", "tracks": [{"track_title": "Mexican Mobsters", "mood": {"1": {"TEXT": "Cool", "ID": "65326"}, "2": {"TEXT": "Wary / Defiant", "ID": "43006"}}, "tempo": {"1": {"TEXT": "Medium Tempo", "ID": "34283"}, "3": {"TEXT": "70s", "ID": "34313"}, "2": {"TEXT": "Medium", "ID": "34290"}}, "track_gnid": "263164882-C9CFBAF98F809F116632F9E965DEEE1B", "track_number": "1", "track_artist_name": ""}, {"track_title": "Deadly Sins", "mood": {"1": {"TEXT": "Cool", "ID": "65326"}, "2": {"TEXT": "Wary / Defiant", "ID": "43006"}}, "tempo": {"1": {"TEXT": "Medium Tempo", "ID": "34283"}, "3": {"TEXT": "80s", "ID": "34316"}, "2": {"TEXT": "Medium", "ID": "34290"}}, "track_gnid": "263164883-AADBE5474A0171EE673FB9A6AA4E58B7", "track_number": "2", "track_artist_name": ""}, {"track_title": "Hide The Pain", "mood": {"1": {"TEXT": "Cool", "ID": "65326"}, "2": {"TEXT": "Wary / Defiant", "ID": "43006"}}, "tempo": {"1": {"TEXT": "Medium Tempo", "ID": "34283"}, "3": {"TEXT": "70s", "ID": "34313"}, "2": {"TEXT": "Medium", "ID": "34290"}}, "track_gnid": "263164884-E0D5B375B701D1828767D9FC49F9592E", "track_number": "3", "track_artist_name": ""}, {"track_title": "Day Of The Dead", "mood": {"1": {"TEXT": "Cool", "ID": "65326"}, "2": {"TEXT": "Wary / Defiant", "ID": "43006"}}, "tempo": {"1": {"TEXT": "Medium Tempo", "ID": "34283"}, "3": {"TEXT": "70s", "ID": "34313"}, "2": {"TEXT": "Medium", "ID": "34290"}}, "track_gnid": "263164885-05173B4D12DB257D508592B6B891B9B6", "track_number": "4", "track_artist_name": ""}, {"track_title": "Payback", "mood": {"1": {"TEXT": "Cool", "ID": "65326"}, "2": {"TEXT": "Wary / Defiant", "ID": "43006"}}, "tempo": {"1": {"TEXT": "Medium Tempo", "ID": "34283"}, "3": {"TEXT": "80s", "ID": "34316"}, "2": {"TEXT": "Medium", "ID": "34290"}}, "track_gnid": "263164886-9C03994EDD79058683CA243D2652DE4D", "track_number": "5", "track_artist_name": ""}, {"track_title": "I Wanna Be Your Man", "mood": {"1": {"TEXT": "Sensual", "ID": "42947"}, "2": {"TEXT": "Intimate", "ID": "42992"}}, "tempo": {"1": {"TEXT": "Slow Tempo", "ID": "34282"}, "3": {"TEXT": "40s", "ID": "34303"}, "2": {"TEXT": "Slow", "ID": "34288"}}, "track_gnid": "263164887-CE901B4EE4EE09CA1E21206B0FA80C86", "track_number": "6", "track_artist_name": ""}, {"track_title": "I'm Fucked Up", "mood": {"1": {"TEXT": "Energizing", "ID": "42961"}, "2": {"TEXT": "Edgy / Sexy", "ID": "43056"}}, "tempo": {"1": {"TEXT": "Medium Tempo", "ID": "34283"}, "3": {"TEXT": "120s", "ID": "34325"}, "2": {"TEXT": "Medium Fast", "ID": "34291"}}, "track_gnid": "263164888-1E9DD41C626BFCDD8BACF2AD79C6BE05", "track_number": "7", "track_artist_name": ""}, {"track_title": "Without You", "mood": {"1": {"TEXT": "Sensual", "ID": "42947"}, "2": {"TEXT": "Intimate", "ID": "42992"}}, "tempo": {"1": {"TEXT": "Medium Tempo", "ID": "34283"}, "3": {"TEXT": "60s", "ID": "34311"}, "2": {"TEXT": "Medium Slow", "ID": "34289"}}, "track_gnid": "263164889-9973192EAB0B2E524FD888222F715793", "track_number": "8", "track_artist_name": ""}, {"track_title": "F@Ck YOU PAY ME", "mood": {"1": {"TEXT": "Cool", "ID": "65326"}, "2": {"TEXT": "Wary / Defiant", "ID": "43006"}}, "tempo": {"1": {"TEXT": "Medium Tempo", "ID": "34283"}, "3": {"TEXT": "80s", "ID": "34316"}, "2": {"TEXT": "Medium", "ID": "34290"}}, "track_gnid": "263164890-66AD5D0161B993460F453279F0E9FE99", "track_number": "9", "track_artist_name": ""}, {"track_title": "Gangsta Muzik (Featuring Murderou", "mood": {"1": {"TEXT": "Energizing", "ID": "42961"}, "2": {"TEXT": "Edgy / Sexy", "ID": "43056"}}, "tempo": {"1": {"TEXT": "Medium Tempo", "ID": "34283"}, "3": {"TEXT": "120s", "ID": "34325"}, "2": {"TEXT": "Medium Fast", "ID": "34291"}}, "track_gnid": "263164891-D19225B884C45F6789E316725794B211", "track_number": "10", "track_artist_name": ""}, {"track_title": "Somebody Please", "mood": {"1": {"TEXT": "Cool", "ID": "65326"}, "2": {"TEXT": "Wary / Defiant", "ID": "43006"}}, "tempo": {"1": {"TEXT": "Medium Tempo", "ID": "34283"}, "3": {"TEXT": "80s", "ID": "34316"}, "2": {"TEXT": "Medium", "ID": "34290"}}, "track_gnid": "263164892-2545340F41D58DF3F13C78D2EFBC972E", "track_number": "11", "track_artist_name": ""}, {"track_title": "Dirty Money", "mood": {"1": {"TEXT": "Cool", "ID": "65326"}, "2": {"TEXT": "Wary / Defiant", "ID": "43006"}}, "tempo": {"1": {"TEXT": "Medium Tempo", "ID": "34283"}, "3": {"TEXT": "80s", "ID": "34316"}, "2": {"TEXT": "Medium", "ID": "34290"}}, "track_gnid": "263164893-F63CEB4273BAD695D87F888979E5B0FC", "track_number": "12", "track_artist_name": ""}, {"track_title": "Let's Party", "mood": {"1": {"TEXT": "Energizing", "ID": "42961"}, "2": {"TEXT": "Edgy / Sexy", "ID": "43056"}}, "tempo": {"1": {"TEXT": "Medium Tempo", "ID": "34283"}, "3": {"TEXT": "70s", "ID": "34313"}, "2": {"TEXT": "Medium", "ID": "34290"}}, "track_gnid": "263164894-2E924C54E0CDBA726F90E5671E9DAF1F", "track_number": "13", "track_artist_name": ""}, {"track_title": "Gangsta Pimpin'", "mood": {"1": {"TEXT": "Cool", "ID": "65326"}, "2": {"TEXT": "Wary / Defiant", "ID": "43006"}}, "tempo": {"1": {"TEXT": "Slow Tempo", "ID": "34282"}, "3": {"TEXT": "40s", "ID": "34303"}, "2": {"TEXT": "Slow", "ID": "34288"}}, "track_gnid": "263164895-76E54BBBDF38C4BD15B7E4FDC7078864", "track_number": "14", "track_artist_name": ""}, {"track_title": "Stress", "mood": {"1": {"TEXT": "Sensual", "ID": "42947"}, "2": {"TEXT": "Intimate", "ID": "42992"}}, "tempo": {"1": {"TEXT": "Medium Tempo", "ID": "34283"}, "3": {"TEXT": "60s", "ID": "34311"}, "2": {"TEXT": "Medium", "ID": "34290"}}, "track_gnid": "263164896-254EDC6B95CFC5ED59D5F50C8E093D4E", "track_number": "15", "track_artist_name": ""}, {"track_title": "Block IS HOT", "mood": {"1": {"TEXT": "Cool", "ID": "65326"}, "2": {"TEXT": "Wary / Defiant", "ID": "43006"}}, "tempo": {"1": {"TEXT": "Medium Tempo", "ID": "34283"}, "3": {"TEXT": "60s", "ID": "34311"}, "2": {"TEXT": "Medium Slow", "ID": "34289"}}, "track_gnid": "263164897-E2A4D769506AD465986012FFD4F61549", "track_number": "16", "track_artist_name": ""}, {"track_title": "Sinful Seven (Featuring XXX Sins)", "mood": {"1": {"TEXT": "Cool", "ID": "65326"}, "2": {"TEXT": "Wary / Defiant", "ID": "43006"}}, "tempo": {"1": {"TEXT": "Medium Tempo", "ID": "34283"}, "3": {"TEXT": "80s", "ID": "34316"}, "2": {"TEXT": "Medium", "ID": "34290"}}, "track_gnid": "263164898-41AD78A9DCC15952E99210ABEA4A3013", "track_number": "17", "track_artist_name": ""}, {"track_title": "Gangsta Love", "mood": {"1": {"TEXT": "Sensual", "ID": "42947"}, "2": {"TEXT": "Intimate", "ID": "42992"}}, "tempo": {"1": {"TEXT": "Medium Tempo", "ID": "34283"}, "3": {"TEXT": "60s", "ID": "34311"}, "2": {"TEXT": "Medium", "ID": "34290"}}, "track_gnid": "263164899-99ABCEBAB14487D391D0D06CECC8C9E0", "track_number": "18", "track_artist_name": ""}, {"track_title": "Hommies In The Can (Featuring Ragg)", "mood": {"1": {"TEXT": "Cool", "ID": "65326"}, "2": {"TEXT": "Wary / Defiant", "ID": "43006"}}, "tempo": {"1": {"TEXT": "Medium Tempo", "ID": "34283"}, "3": {"TEXT": "80s", "ID": "34316"}, "2": {"TEXT": "Medium", "ID": "34290"}}, "track_gnid": "263164900-8877EF750944DC35692909F0D365E34E", "track_number": "19", "track_artist_name": ""}, {"track_title": "Criminal Wayz", "mood": {"1": {"TEXT": "Aggressive", "ID": "42958"}, "2": {"TEXT": "Chaotic / Intense", "ID": "43033"}}, "tempo": {"1": {"TEXT": "Fast Tempo", "ID": "43078"}, "3": {"TEXT": "180s", "ID": "34335"}, "2": {"TEXT": "Very Fast", "ID": "34293"}}, "track_gnid": "263164901-4E5306DE7FCCA3DE21AAF3C5A92F4CEC", "track_number": "20", "track_artist_name": ""}], "xid": "", "album_gnid": "263164881-AC04759D3541AE46D25F6AE7F455A09B", "artist_origin": {}, "genre": {"1": {"TEXT": "Urban", "ID": "25316"}, "3": {"TEXT": "General Hip-Hop/Rap", "ID": "35559"}, "2": {"TEXT": "Western Hip-Hop/Rap", "ID": "35503"}}, "album_title": "Greatest Hits", "track_artist_name": "", "artist_type": {}}