{"artist_era": {}, "tempo": {}, "artist_origin": {}, "album_art_url": "http://akamai-b.cdn.cddbp.net/cds/2.0/cover/5B8A/5F15/32C7/34B4_medium_front.jpg?cid=1247529661", "track_gnid": "", "review_url": "", "track_number": "", "artist_bio_url": "", "artist_type": {}, "tracks": [{"tempo": {"2": {"TEXT": "Medium", "ID": "34290"}, "3": {"TEXT": "80s", "ID": "34316"}, "1": {"TEXT": "Medium Tempo", "ID": "34283"}}, "mood": {"2": {"TEXT": "Enigmatic / Mysterious", "ID": "42995"}, "1": {"TEXT": "Somber", "ID": "42948"}}, "track_title": "Darkening Skies", "track_gnid": "158470266-94D0E306838ABE0F115809C73A932C1A", "track_number": "1", "track_artist_name": ""}, {"tempo": {"2": {"TEXT": "Medium Fast", "ID": "34291"}, "3": {"TEXT": "110s", "ID": "34323"}, "1": {"TEXT": "Medium Tempo", "ID": "34283"}}, "mood": {"2": {"TEXT": "Hard Dark Excitement", "ID": "43036"}, "1": {"TEXT": "Defiant", "ID": "42951"}}, "track_title": "Frailty Of The Flesh", "track_gnid": "158470267-7C077F4A87F114517387D438175C9943", "track_number": "2", "track_artist_name": ""}, {"tempo": {"2": {"TEXT": "Medium Fast", "ID": "34291"}, "3": {"TEXT": "110s", "ID": "34323"}, "1": {"TEXT": "Medium Tempo", "ID": "34283"}}, "mood": {"2": {"TEXT": "Hard Dark Excitement", "ID": "43036"}, "1": {"TEXT": "Defiant", "ID": "42951"}}, "track_title": "Sealed Fate", "track_gnid": "158470268-67B7BBE4F546B9B64B4BFA35764E5D28", "track_number": "3", "track_artist_name": ""}, {"tempo": {"2": {"TEXT": "Medium Fast", "ID": "34291"}, "3": {"TEXT": "100s", "ID": "34320"}, "1": {"TEXT": "Medium Tempo", "ID": "34283"}}, "mood": {"2": {"TEXT": "Hard Dark Excitement", "ID": "43036"}, "1": {"TEXT": "Defiant", "ID": "42951"}}, "track_title": "Frozen Hell", "track_gnid": "158470269-F86B2B2E6A6FD5A49E66898C0EC08977", "track_number": "4", "track_artist_name": ""}, {"tempo": {"2": {"TEXT": "Medium Fast", "ID": "34291"}, "3": {"TEXT": "100s", "ID": "34320"}, "1": {"TEXT": "Medium Tempo", "ID": "34283"}}, "mood": {"2": {"TEXT": "Hard Dark Excitement", "ID": "43036"}, "1": {"TEXT": "Defiant", "ID": "42951"}}, "track_title": "Attack Imminent", "track_gnid": "158470270-0E253202A2071DE13340B93855957231", "track_number": "5", "track_artist_name": ""}, {"tempo": {"2": {"TEXT": "Medium Fast", "ID": "34291"}, "3": {"TEXT": "110s", "ID": "34323"}, "1": {"TEXT": "Medium Tempo", "ID": "34283"}}, "mood": {"2": {"TEXT": "Hard Dark Excitement", "ID": "43036"}, "1": {"TEXT": "Defiant", "ID": "42951"}}, "track_title": "The Morlocks Tomb", "track_gnid": "158470271-D351884100AE8DBF64014F878FC09A88", "track_number": "6", "track_artist_name": ""}, {"tempo": {"2": {"TEXT": "Medium Fast", "ID": "34291"}, "3": {"TEXT": "100s", "ID": "34320"}, "1": {"TEXT": "Medium Tempo", "ID": "34283"}}, "mood": {"2": {"TEXT": "Wild / Rowdy", "ID": "65353"}, "1": {"TEXT": "Rowdy", "ID": "65330"}}, "track_title": "Storm The Gates", "track_gnid": "158470272-141244C6A8FC2A1FAB399D154E367672", "track_number": "7", "track_artist_name": ""}, {"tempo": {"2": {"TEXT": "Medium Fast", "ID": "34291"}, "3": {"TEXT": "100s", "ID": "34320"}, "1": {"TEXT": "Medium Tempo", "ID": "34283"}}, "mood": {"2": {"TEXT": "Hard Dark Excitement", "ID": "43036"}, "1": {"TEXT": "Defiant", "ID": "42951"}}, "track_title": "The Dead Will March", "track_gnid": "158470273-4819B5FCA027D76821CE4DBB858D07FC", "track_number": "8", "track_artist_name": ""}, {"tempo": {"2": {"TEXT": "Medium Fast", "ID": "34291"}, "3": {"TEXT": "110s", "ID": "34323"}, "1": {"TEXT": "Medium Tempo", "ID": "34283"}}, "mood": {"2": {"TEXT": "Hard Dark Excitement", "ID": "43036"}, "1": {"TEXT": "Defiant", "ID": "42951"}}, "track_title": "Awaiting Evil", "track_gnid": "158470274-8768CA3362279D98E5A8582BA60330F0", "track_number": "9", "track_artist_name": ""}], "track_artist_name": "", "album_artist_name": "Hatchet", "artist_image_url": "", "mood": {}, "track_title": "", "album_gnid": "158470265-A083FD716E9AF3597EAE809A50E43183", "genre": {"2": {"TEXT": "Metal", "ID": "35478"}, "3": {"TEXT": "Heavy Metal", "ID": "25484"}, "1": {"TEXT": "Rock", "ID": "25313"}}, "album_title": "Awaiting Evil", "album_year": "2008", "xid": "", "radio_id": ""}