{"track_title": "", "album_artist_name": "The Brains", "mood": {}, "artist_bio_url": "", "artist_image_url": "", "artist_era": {"1": {"TEXT": "1970s", "ID": "29486"}, "2": {"TEXT": "Late 1970s", "ID": "29505"}}, "album_year": "2010", "radio_id": "", "tempo": {}, "track_gnid": "", "track_number": "", "review_url": "", "album_art_url": "http://akamai-b.cdn.cddbp.net/cds/2.0/cover/BA81/8455/7499/D180_medium_front.jpg?cid=1247529661", "tracks": [{"track_title": "R.I.P.", "mood": {"1": {"TEXT": "Aggressive", "ID": "42958"}, "2": {"TEXT": "Aggressive Power", "ID": "43034"}}, "tempo": {"1": {"TEXT": "Fast Tempo", "ID": "43078"}, "3": {"TEXT": "150s", "ID": "34331"}, "2": {"TEXT": "Fast", "ID": "34292"}}, "track_gnid": "211018451-33979744761E3926A0389054F626D609", "track_number": "1", "track_artist_name": ""}, {"track_title": "We'll Rise", "mood": {"1": {"TEXT": "Defiant", "ID": "42951"}, "2": {"TEXT": "Hard Dark Excitement", "ID": "43036"}}, "tempo": {"1": {"TEXT": "Fast Tempo", "ID": "43078"}, "3": {"TEXT": "160s", "ID": "34332"}, "2": {"TEXT": "Fast", "ID": "34292"}}, "track_gnid": "211018452-1A8CC6AC090F860ABE4132A8B249074D", "track_number": "2", "track_artist_name": ""}, {"track_title": "We Gotta Go", "mood": {"1": {"TEXT": "Defiant", "ID": "42951"}, "2": {"TEXT": "Hard Dark Excitement", "ID": "43036"}}, "tempo": {"1": {"TEXT": "Medium Tempo", "ID": "34283"}, "3": {"TEXT": "100s", "ID": "34320"}, "2": {"TEXT": "Medium Fast", "ID": "34291"}}, "track_gnid": "211018453-AFFFD9E24948CE6631E88D7C037EC815", "track_number": "3", "track_artist_name": ""}, {"track_title": "Screaming", "mood": {"1": {"TEXT": "Defiant", "ID": "42951"}, "2": {"TEXT": "Hard Positive Excitement", "ID": "43037"}}, "tempo": {"1": {"TEXT": "Fast Tempo", "ID": "43078"}, "3": {"TEXT": "160s", "ID": "34332"}, "2": {"TEXT": "Fast", "ID": "34292"}}, "track_gnid": "211018454-A59230FB97326F210D8F168CF11BF5DB", "track_number": "4", "track_artist_name": ""}, {"track_title": "Apres Cette Nuit", "mood": {"1": {"TEXT": "Aggressive", "ID": "42958"}, "2": {"TEXT": "Heavy Triumphant", "ID": "43032"}}, "tempo": {"1": {"TEXT": "Fast Tempo", "ID": "43078"}, "3": {"TEXT": "140s", "ID": "34538"}, "2": {"TEXT": "Fast", "ID": "34292"}}, "track_gnid": "211018455-FD9B7CD2FFAC4D6E07E639400E89744B", "track_number": "5", "track_artist_name": ""}, {"track_title": "Devil's Crossroad", "mood": {"1": {"TEXT": "Defiant", "ID": "42951"}, "2": {"TEXT": "Hard Dark Excitement", "ID": "43036"}}, "tempo": {"1": {"TEXT": "Fast Tempo", "ID": "43078"}, "3": {"TEXT": "160s", "ID": "34332"}, "2": {"TEXT": "Fast", "ID": "34292"}}, "track_gnid": "211018456-CD975D8B6D130D1E7CB515D3921E20CC", "track_number": "6", "track_artist_name": ""}, {"track_title": "Sweeter Than Wine", "mood": {"1": {"TEXT": "Rowdy", "ID": "65330"}, "2": {"TEXT": "Driving Dark Groove", "ID": "43035"}}, "tempo": {"1": {"TEXT": "Medium Tempo", "ID": "34283"}, "3": {"TEXT": "70s", "ID": "34313"}, "2": {"TEXT": "Medium", "ID": "34290"}}, "track_gnid": "211018457-2229B8773066E7130BA18B3B6FE171D0", "track_number": "7", "track_artist_name": ""}, {"track_title": "Spaghetti Western", "mood": {"1": {"TEXT": "Rowdy", "ID": "65330"}, "2": {"TEXT": "Wild / Rowdy", "ID": "65353"}}, "tempo": {"1": {"TEXT": "Fast Tempo", "ID": "43078"}, "3": {"TEXT": "150s", "ID": "34331"}, "2": {"TEXT": "Fast", "ID": "34292"}}, "track_gnid": "211018458-35F49173FE8450428C46D056D30FF2E2", "track_number": "8", "track_artist_name": ""}, {"track_title": "As I Stand", "mood": {"1": {"TEXT": "Aggressive", "ID": "42958"}, "2": {"TEXT": "Heavy Triumphant", "ID": "43032"}}, "tempo": {"1": {"TEXT": "Fast Tempo", "ID": "43078"}, "3": {"TEXT": "160s", "ID": "34332"}, "2": {"TEXT": "Fast", "ID": "34292"}}, "track_gnid": "211018459-F92B20476BAFEDA0BF3B97BBF75C13D3", "track_number": "9", "track_artist_name": ""}, {"track_title": "Zombie Nation", "mood": {"1": {"TEXT": "Brooding", "ID": "65329"}, "2": {"TEXT": "Alienated / Brooding", "ID": "43028"}}, "tempo": {"1": {"TEXT": "Medium Tempo", "ID": "34283"}, "3": {"TEXT": "70s", "ID": "34313"}, "2": {"TEXT": "Medium", "ID": "34290"}}, "track_gnid": "211018460-27D58280E905777846F191FD24ADFEB6", "track_number": "10", "track_artist_name": ""}, {"track_title": "I Don't Care", "mood": {"1": {"TEXT": "Defiant", "ID": "42951"}, "2": {"TEXT": "Heavy Brooding", "ID": "43030"}}, "tempo": {"1": {"TEXT": "Medium Tempo", "ID": "34283"}, "3": {"TEXT": "100s", "ID": "34320"}, "2": {"TEXT": "Medium Fast", "ID": "34291"}}, "track_gnid": "211018461-FB3319CD2FC6A8EFE230ED49408A032D", "track_number": "11", "track_artist_name": ""}, {"track_title": "Evil Never Dies", "mood": {"1": {"TEXT": "Defiant", "ID": "42951"}, "2": {"TEXT": "Hard Dark Excitement", "ID": "43036"}}, "tempo": {"1": {"TEXT": "Medium Tempo", "ID": "34283"}, "3": {"TEXT": "100s", "ID": "34320"}, "2": {"TEXT": "Medium Fast", "ID": "34291"}}, "track_gnid": "211018462-16AF36097014812E2FD4DCC39DC1B03B", "track_number": "12", "track_artist_name": ""}, {"track_title": "Mexikaners", "mood": {"1": {"TEXT": "Defiant", "ID": "42951"}, "2": {"TEXT": "Hard Dark Excitement", "ID": "43036"}}, "tempo": {"1": {"TEXT": "Medium Tempo", "ID": "34283"}, "3": {"TEXT": "100s", "ID": "34320"}, "2": {"TEXT": "Medium Fast", "ID": "34291"}}, "track_gnid": "211018463-BCC4DCAEC662EC8A1A8D7F8991CECF44", "track_number": "13", "track_artist_name": ""}, {"track_title": "Enjoy The Silence", "mood": {"1": {"TEXT": "Defiant", "ID": "42951"}, "2": {"TEXT": "Hard Dark Excitement", "ID": "43036"}}, "tempo": {"1": {"TEXT": "Fast Tempo", "ID": "43078"}, "3": {"TEXT": "150s", "ID": "34331"}, "2": {"TEXT": "Fast", "ID": "34292"}}, "track_gnid": "211018464-E49B53973AC81A284A80597A4BAC592D", "track_number": "14", "track_artist_name": ""}], "xid": "", "album_gnid": "211018450-2CA3E797E3B5C7A9C01415A35D9C73A7", "artist_origin": {"1": {"TEXT": "North America", "ID": "29889"}, "3": {"TEXT": "New York", "ID": "30199"}, "2": {"TEXT": "United States", "ID": "29908"}, "4": {"TEXT": "New York City", "ID": "30634"}}, "genre": {"1": {"TEXT": "Alternative & Punk", "ID": "25312"}, "3": {"TEXT": "New Wave Pop", "ID": "35552"}, "2": {"TEXT": "New Wave Pop", "ID": "65023"}}, "album_title": "Zombie Nation", "track_artist_name": "", "artist_type": {"1": {"TEXT": "Male", "ID": "29422"}, "2": {"TEXT": "Male Group", "ID": "29436"}}}