{"track_title": "", "album_artist_name": "Thought Forms", "mood": {}, "artist_bio_url": "", "artist_image_url": "", "artist_era": {}, "album_year": "2009", "radio_id": "", "tempo": {}, "track_gnid": "", "track_number": "", "review_url": "", "album_art_url": "http://akamai-b.cdn.cddbp.net/cds/2.0/cover/7D0D/F315/344A/9F31_medium_front.jpg?cid=1247529661", "tracks": [{"track_title": "Twenty Satellites on My Hill", "mood": {"1": {"TEXT": "Somber", "ID": "42948"}, "2": {"TEXT": "Creepy / Ominous", "ID": "42996"}}, "tempo": {"1": {"TEXT": "Medium Tempo", "ID": "34283"}, "3": {"TEXT": "50s", "ID": "34307"}, "2": {"TEXT": "Medium Slow", "ID": "34289"}}, "track_gnid": "181997277-A81616E8C4EFABA08971D1E804484660", "track_number": "1", "track_artist_name": ""}, {"track_title": "Industry", "mood": {"1": {"TEXT": "Brooding", "ID": "65329"}, "2": {"TEXT": "Alienated / Brooding", "ID": "43028"}}, "tempo": {"1": {"TEXT": "Medium Tempo", "ID": "34283"}, "3": {"TEXT": "90s", "ID": "34318"}, "2": {"TEXT": "Medium Fast", "ID": "34291"}}, "track_gnid": "181997278-081A363973EDD3DC799411665721B24B", "track_number": "2", "track_artist_name": ""}, {"track_title": "Dust Magic", "mood": {"1": {"TEXT": "Brooding", "ID": "65329"}, "2": {"TEXT": "Dreamy Brooding", "ID": "43025"}}, "tempo": {"1": {"TEXT": "Medium Tempo", "ID": "34283"}, "3": {"TEXT": "90s", "ID": "34318"}, "2": {"TEXT": "Medium Fast", "ID": "34291"}}, "track_gnid": "181997279-056B3E2D35B64C173072A141582B7B78", "track_number": "3", "track_artist_name": ""}, {"track_title": "Nothing Is as Easy as You Think", "mood": {"1": {"TEXT": "Melancholy", "ID": "42949"}, "2": {"TEXT": "Light Melancholy", "ID": "65343"}}, "tempo": {"1": {"TEXT": "Medium Tempo", "ID": "34283"}, "3": {"TEXT": "50s", "ID": "34307"}, "2": {"TEXT": "Medium Slow", "ID": "34289"}}, "track_gnid": "181997280-518E901ED14CF0B171B9CA0D3E42541F", "track_number": "4", "track_artist_name": ""}, {"track_title": "Sonny", "mood": {"1": {"TEXT": "Somber", "ID": "42948"}, "2": {"TEXT": "Creepy / Ominous", "ID": "42996"}}, "tempo": {"1": {"TEXT": "Slow Tempo", "ID": "34282"}, "3": {"TEXT": "30s", "ID": "34300"}, "2": {"TEXT": "Very Slow", "ID": "34287"}}, "track_gnid": "181997281-1FD1D8DA8FFFD9EF890A002D37FE0EC5", "track_number": "5", "track_artist_name": ""}, {"track_title": "We Would Be so Happy If...", "mood": {"1": {"TEXT": "Brooding", "ID": "65329"}, "2": {"TEXT": "Dreamy Brooding", "ID": "43025"}}, "tempo": {"1": {"TEXT": "Medium Tempo", "ID": "34283"}, "3": {"TEXT": "70s", "ID": "34313"}, "2": {"TEXT": "Medium", "ID": "34290"}}, "track_gnid": "181997282-838F832F6D934407AADB2B8974CA3D5C", "track_number": "6", "track_artist_name": ""}, {"track_title": "David, 18", "mood": {"1": {"TEXT": "Brooding", "ID": "65329"}, "2": {"TEXT": "Dreamy Brooding", "ID": "43025"}}, "tempo": {"1": {"TEXT": "Medium Tempo", "ID": "34283"}, "3": {"TEXT": "70s", "ID": "34313"}, "2": {"TEXT": "Medium", "ID": "34290"}}, "track_gnid": "181997283-EE6C2F73014509FABD9665A64BA3B525", "track_number": "7", "track_artist_name": ""}, {"track_title": "Mr Steve Has Eaten Your Dog", "mood": {"1": {"TEXT": "Brooding", "ID": "65329"}, "2": {"TEXT": "Alienated / Brooding", "ID": "43028"}}, "tempo": {"1": {"TEXT": "Fast Tempo", "ID": "43078"}, "3": {"TEXT": "130s", "ID": "34537"}, "2": {"TEXT": "Fast", "ID": "34292"}}, "track_gnid": "181997284-09DF0AD13F675F75A7EDB336AD490409", "track_number": "8", "track_artist_name": ""}, {"track_title": "Maggie", "mood": {"1": {"TEXT": "Somber", "ID": "42948"}, "2": {"TEXT": "Dark Cosmic", "ID": "42994"}}, "tempo": {"1": {"TEXT": "Medium Tempo", "ID": "34283"}, "3": {"TEXT": "90s", "ID": "34318"}, "2": {"TEXT": "Medium Fast", "ID": "34291"}}, "track_gnid": "181997285-C86420359839BD306DEF8F245109A5E1", "track_number": "9", "track_artist_name": ""}], "xid": "", "album_gnid": "181997276-46B4A13137286814F7658F0D08738069", "artist_origin": {}, "genre": {"1": {"TEXT": "Alternative & Punk", "ID": "25312"}, "3": {"TEXT": "Alternative Rock", "ID": "25420"}, "2": {"TEXT": "Alternative", "ID": "25322"}}, "album_title": "Thought Forms", "track_artist_name": "", "artist_type": {}}