{"artist_era": {"2": {"TEXT": "Late 2000's", "ID": "29493"}, "1": {"TEXT": "2000's", "ID": "29483"}}, "tempo": {}, "artist_origin": {"2": {"TEXT": "United States", "ID": "29908"}, "4": {"TEXT": "New York City", "ID": "30634"}, "3": {"TEXT": "New York", "ID": "30199"}, "1": {"TEXT": "North America", "ID": "29889"}}, "album_art_url": "http://akamai-b.cdn.cddbp.net/cds/2.0/cover/9E5B/B0A1/6AF5/B892_medium_front.jpg?cid=1247529661", "track_gnid": "", "review_url": "", "track_number": "", "artist_bio_url": "", "artist_type": {"2": {"TEXT": "Male Group", "ID": "29436"}, "1": {"TEXT": "Male", "ID": "29422"}}, "tracks": [{"tempo": {"2": {"TEXT": "Medium", "ID": "34290"}, "3": {"TEXT": "80s", "ID": "34316"}, "1": {"TEXT": "Medium Tempo", "ID": "34283"}}, "mood": {"2": {"TEXT": "Energetic Anxious", "ID": "65351"}, "1": {"TEXT": "Urgent", "ID": "42955"}}, "track_title": "Alone", "track_gnid": "271810465-71A4C5058EF087C299FA733A96163701", "track_number": "1", "track_artist_name": ""}, {"tempo": {"2": {"TEXT": "Medium", "ID": "34290"}, "3": {"TEXT": "70s", "ID": "34313"}, "1": {"TEXT": "Medium Tempo", "ID": "34283"}}, "mood": {"2": {"TEXT": "Alienated / Brooding", "ID": "43028"}, "1": {"TEXT": "Brooding", "ID": "65329"}}, "track_title": "You Are The One", "track_gnid": "271810466-1C7AD0EB86F4AE997C6E2ADCF9443C95", "track_number": "2", "track_artist_name": ""}, {"tempo": {"2": {"TEXT": "Fast", "ID": "34292"}, "3": {"TEXT": "160s", "ID": "34332"}, "1": {"TEXT": "Fast Tempo", "ID": "43078"}}, "mood": {"2": {"TEXT": "Chaotic / Intense", "ID": "43033"}, "1": {"TEXT": "Aggressive", "ID": "42958"}}, "track_title": "Mind Control", "track_gnid": "271810467-D0E128DE4C732096B194D22DF0BF5EBD", "track_number": "3", "track_artist_name": ""}, {"tempo": {"2": {"TEXT": "Medium Fast", "ID": "34291"}, "3": {"TEXT": "120s", "ID": "34325"}, "1": {"TEXT": "Medium Tempo", "ID": "34283"}}, "mood": {"2": {"TEXT": "Heavy Brooding", "ID": "43030"}, "1": {"TEXT": "Defiant", "ID": "42951"}}, "track_title": "Worship", "track_gnid": "271810468-93EB09227CC93D847459620298EDBD64", "track_number": "4", "track_artist_name": ""}, {"tempo": {"2": {"TEXT": "Medium", "ID": "34290"}, "3": {"TEXT": "70s", "ID": "34313"}, "1": {"TEXT": "Medium Tempo", "ID": "34283"}}, "mood": {"2": {"TEXT": "Alienated / Brooding", "ID": "43028"}, "1": {"TEXT": "Brooding", "ID": "65329"}}, "track_title": "Fear", "track_gnid": "271810469-7797CA44980E5A9EAFCF23E494DFEC7A", "track_number": "5", "track_artist_name": ""}, {"tempo": {"2": {"TEXT": "Medium Fast", "ID": "34291"}, "3": {"TEXT": "100s", "ID": "34320"}, "1": {"TEXT": "Medium Tempo", "ID": "34283"}}, "mood": {"2": {"TEXT": "Alienated / Brooding", "ID": "43028"}, "1": {"TEXT": "Brooding", "ID": "65329"}}, "track_title": "Dissolved", "track_gnid": "271810470-AF212B40A22B7A7EE32465DD2A62E0B7", "track_number": "6", "track_artist_name": ""}, {"tempo": {"2": {"TEXT": "Very Fast", "ID": "34293"}, "3": {"TEXT": "180s", "ID": "34335"}, "1": {"TEXT": "Fast Tempo", "ID": "43078"}}, "mood": {"2": {"TEXT": "Chaotic / Intense", "ID": "43033"}, "1": {"TEXT": "Aggressive", "ID": "42958"}}, "track_title": "Why I Can't Cry Anymore", "track_gnid": "271810471-0B9F6DDA43220C2FA31A63DCAB35B9E3", "track_number": "7", "track_artist_name": ""}, {"tempo": {"2": {"TEXT": "Fast", "ID": "34292"}, "3": {"TEXT": "170s", "ID": "34333"}, "1": {"TEXT": "Fast Tempo", "ID": "43078"}}, "mood": {"2": {"TEXT": "Chaotic / Intense", "ID": "43033"}, "1": {"TEXT": "Aggressive", "ID": "42958"}}, "track_title": "Revenge", "track_gnid": "271810472-E99440897EB8239F3F2BC52721688494", "track_number": "8", "track_artist_name": ""}, {"tempo": {"2": {"TEXT": "Medium", "ID": "34290"}, "3": {"TEXT": "80s", "ID": "34316"}, "1": {"TEXT": "Medium Tempo", "ID": "34283"}}, "mood": {"2": {"TEXT": "Energetic Anxious", "ID": "65351"}, "1": {"TEXT": "Urgent", "ID": "42955"}}, "track_title": "And I'm Up", "track_gnid": "271810473-A4A2B49B5488E3600EB00015C3B106A9", "track_number": "9", "track_artist_name": ""}, {"tempo": {"2": {"TEXT": "Fast", "ID": "34292"}, "3": {"TEXT": "140s", "ID": "34538"}, "1": {"TEXT": "Fast Tempo", "ID": "43078"}}, "mood": {"2": {"TEXT": "Alienated / Brooding", "ID": "43028"}, "1": {"TEXT": "Brooding", "ID": "65329"}}, "track_title": "Slide", "track_gnid": "271810474-1D445481F2B0A087CBBD0C399ACEC14C", "track_number": "10", "track_artist_name": ""}, {"tempo": {"2": {"TEXT": "Medium Fast", "ID": "34291"}, "3": {"TEXT": "90s", "ID": "34318"}, "1": {"TEXT": "Medium Tempo", "ID": "34283"}}, "mood": {"2": {"TEXT": "Heavy Brooding", "ID": "43030"}, "1": {"TEXT": "Defiant", "ID": "42951"}}, "track_title": "Leaving Tomorrow", "track_gnid": "271810475-2F479945748C6AF04F78FFDC21C9B0B1", "track_number": "11", "track_artist_name": ""}], "track_artist_name": "", "album_artist_name": "A Place To Bury Strangers", "artist_image_url": "", "mood": {}, "track_title": "", "album_gnid": "271810464-646F7414D27688C7FB7DC7D56665ED0E", "genre": {"2": {"TEXT": "Indie Rock", "ID": "35477"}, "3": {"TEXT": "Shoegazer", "ID": "25449"}, "1": {"TEXT": "Alternative & Punk", "ID": "25312"}}, "album_title": "Worship", "album_year": "2012", "xid": "", "radio_id": ""}