{"artist_era": {}, "tempo": {}, "artist_origin": {}, "album_art_url": "", "track_gnid": "", "review_url": "", "track_number": "", "artist_bio_url": "", "artist_type": {}, "tracks": [{"tempo": {"2": {"TEXT": "Fast", "ID": "34292"}, "3": {"TEXT": "150s", "ID": "34331"}, "1": {"TEXT": "Fast Tempo", "ID": "43078"}}, "mood": {"2": {"TEXT": "Aggressive Power", "ID": "43034"}, "1": {"TEXT": "Aggressive", "ID": "42958"}}, "track_title": "1000 Words", "track_gnid": "81738460-9A25DF369DC5359F842AD13935F89C75", "track_number": "1", "track_artist_name": ""}, {"tempo": {"2": {"TEXT": "Medium Fast", "ID": "34291"}, "3": {"TEXT": "110s", "ID": "34323"}, "1": {"TEXT": "Medium Tempo", "ID": "34283"}}, "mood": {"2": {"TEXT": "Hard Dark Excitement", "ID": "43036"}, "1": {"TEXT": "Defiant", "ID": "42951"}}, "track_title": "Found My Niche", "track_gnid": "81738461-F1D34496A4D1EBA9DC58564FF22F9968", "track_number": "2", "track_artist_name": ""}, {"tempo": {"2": {"TEXT": "Fast", "ID": "34292"}, "3": {"TEXT": "130s", "ID": "34537"}, "1": {"TEXT": "Fast Tempo", "ID": "43078"}}, "mood": {"2": {"TEXT": "Hard Dark Excitement", "ID": "43036"}, "1": {"TEXT": "Defiant", "ID": "42951"}}, "track_title": "So Move On", "track_gnid": "81738462-EC075EC0558CA44938D706E162E40B87", "track_number": "3", "track_artist_name": ""}, {"tempo": {"2": {"TEXT": "Medium Fast", "ID": "34291"}, "3": {"TEXT": "110s", "ID": "34323"}, "1": {"TEXT": "Medium Tempo", "ID": "34283"}}, "mood": {"2": {"TEXT": "Hard Dark Excitement", "ID": "43036"}, "1": {"TEXT": "Defiant", "ID": "42951"}}, "track_title": "Because Of You", "track_gnid": "81738463-D6B7D992A30A998204A9CAF70F3A52FA", "track_number": "4", "track_artist_name": ""}, {"tempo": {"2": {"TEXT": "Medium Fast", "ID": "34291"}, "3": {"TEXT": "110s", "ID": "34323"}, "1": {"TEXT": "Medium Tempo", "ID": "34283"}}, "mood": {"2": {"TEXT": "Hard Dark Excitement", "ID": "43036"}, "1": {"TEXT": "Defiant", "ID": "42951"}}, "track_title": "Never Said A Word", "track_gnid": "81738464-CC951D88033FB6F22917DFCB5D2B5F0A", "track_number": "5", "track_artist_name": ""}, {"tempo": {"2": {"TEXT": "Medium Fast", "ID": "34291"}, "3": {"TEXT": "110s", "ID": "34323"}, "1": {"TEXT": "Medium Tempo", "ID": "34283"}}, "mood": {"2": {"TEXT": "Hard Dark Excitement", "ID": "43036"}, "1": {"TEXT": "Defiant", "ID": "42951"}}, "track_title": "Exhale", "track_gnid": "81738465-7223E38E8127E196E25983702A2AA905", "track_number": "6", "track_artist_name": ""}, {"tempo": {"2": {"TEXT": "Medium Fast", "ID": "34291"}, "3": {"TEXT": "110s", "ID": "34323"}, "1": {"TEXT": "Medium Tempo", "ID": "34283"}}, "mood": {"2": {"TEXT": "Hard Dark Excitement", "ID": "43036"}, "1": {"TEXT": "Defiant", "ID": "42951"}}, "track_title": "Wake Me When It's Over", "track_gnid": "81738466-64AD53FC18232ACBE61378ADA1CC2360", "track_number": "7", "track_artist_name": ""}, {"tempo": {"2": {"TEXT": "Medium Fast", "ID": "34291"}, "3": {"TEXT": "110s", "ID": "34323"}, "1": {"TEXT": "Medium Tempo", "ID": "34283"}}, "mood": {"2": {"TEXT": "Hard Dark Excitement", "ID": "43036"}, "1": {"TEXT": "Defiant", "ID": "42951"}}, "track_title": "On The Line", "track_gnid": "81738467-0506D2E50F4FE7081EF0F08FC61269D4", "track_number": "8", "track_artist_name": ""}, {"tempo": {"2": {"TEXT": "Fast", "ID": "34292"}, "3": {"TEXT": "150s", "ID": "34331"}, "1": {"TEXT": "Fast Tempo", "ID": "43078"}}, "mood": {"2": {"TEXT": "Hard Dark Excitement", "ID": "43036"}, "1": {"TEXT": "Defiant", "ID": "42951"}}, "track_title": "Just Let Go", "track_gnid": "81738468-661B84C44C8264883DBE4A5250715839", "track_number": "9", "track_artist_name": ""}, {"tempo": {"2": {"TEXT": "Medium Fast", "ID": "34291"}, "3": {"TEXT": "110s", "ID": "34323"}, "1": {"TEXT": "Medium Tempo", "ID": "34283"}}, "mood": {"2": {"TEXT": "Aggressive Power", "ID": "43034"}, "1": {"TEXT": "Aggressive", "ID": "42958"}}, "track_title": "Don't Tell Me", "track_gnid": "81738469-667041AA3C6FADAB7B5743A0290A8469", "track_number": "10", "track_artist_name": ""}, {"tempo": {"2": {"TEXT": "Medium Fast", "ID": "34291"}, "3": {"TEXT": "110s", "ID": "34323"}, "1": {"TEXT": "Medium Tempo", "ID": "34283"}}, "mood": {"2": {"TEXT": "Hard Dark Excitement", "ID": "43036"}, "1": {"TEXT": "Defiant", "ID": "42951"}}, "track_title": "Overlooked", "track_gnid": "81738470-FA03C938EC8427DDE67EBD2FBC56B08F", "track_number": "11", "track_artist_name": ""}, {"tempo": {"2": {"TEXT": "Medium Fast", "ID": "34291"}, "3": {"TEXT": "120s", "ID": "34325"}, "1": {"TEXT": "Medium Tempo", "ID": "34283"}}, "mood": {"2": {"TEXT": "Hard Dark Excitement", "ID": "43036"}, "1": {"TEXT": "Defiant", "ID": "42951"}}, "track_title": "Why I Am This Way", "track_gnid": "81738471-1660FF1208CADEB3E97AFA10E9C17DB3", "track_number": "12", "track_artist_name": ""}], "track_artist_name": "", "album_artist_name": "Allegiance", "artist_image_url": "", "mood": {}, "track_title": "", "album_gnid": "81738459-60FD2EEC26BEDB02D99948EEB97354D5", "genre": {"2": {"TEXT": "Punk", "ID": "35474"}, "3": {"TEXT": "Hardcore Punk", "ID": "25433"}, "1": {"TEXT": "Alternative & Punk", "ID": "25312"}}, "album_title": "Overlooked", "album_year": "2005", "xid": "", "radio_id": ""}