{"track_title": "", "album_artist_name": "Drudkh", "mood": {}, "artist_bio_url": "", "artist_image_url": "", "artist_era": {"1": {"TEXT": "2000's", "ID": "29483"}}, "album_year": "2012", "radio_id": "", "tempo": {}, "track_gnid": "", "track_number": "", "review_url": "", "album_art_url": "http://akamai-b.cdn.cddbp.net/cds/2.0/cover/4ADB/07C6/9287/8DA8_medium_front.jpg?cid=1247529661", "tracks": [{"track_title": "Fading (\u0417\u0430\u0432\u043c\u0438\u0440\u0430\u043d\u043d\u044f)", "mood": {"1": {"TEXT": "Brooding", "ID": "65329"}, "2": {"TEXT": "Alienated / Brooding", "ID": "43028"}}, "tempo": {"1": {"TEXT": "Medium Tempo", "ID": "34283"}, "3": {"TEXT": "110s", "ID": "34323"}, "2": {"TEXT": "Medium Fast", "ID": "34291"}}, "track_gnid": "197593338-35732D9AC39AD2D530364DE9DAF3BD1D", "track_number": "1", "track_artist_name": ""}, {"track_title": "Summoning the Rain (\u0417\u0430\u043a\u043b\u0438\u043a\u0430\u044e\u0447\u0438 \u0414\u043e\u0449)", "mood": {"1": {"TEXT": "Brooding", "ID": "65329"}, "2": {"TEXT": "Alienated / Brooding", "ID": "43028"}}, "tempo": {"1": {"TEXT": "Medium Tempo", "ID": "34283"}, "3": {"TEXT": "80s", "ID": "34316"}, "2": {"TEXT": "Medium", "ID": "34290"}}, "track_gnid": "197593339-C6DCDC6CF009E2490DAA2CE88A9F751C", "track_number": "2", "track_artist_name": ""}, {"track_title": "Glare of Autumn (\u0412\u0456\u0434\u0431\u043b\u0438\u0441\u043a\u0438 \u041e\u0441\u0435\u043d\u0456)", "mood": {"1": {"TEXT": "Brooding", "ID": "65329"}, "2": {"TEXT": "Alienated / Brooding", "ID": "43028"}}, "tempo": {"1": {"TEXT": "Fast Tempo", "ID": "43078"}, "3": {"TEXT": "130s", "ID": "34537"}, "2": {"TEXT": "Fast", "ID": "34292"}}, "track_gnid": "197593340-E00C5F778468EF23EB8FC235D953166A", "track_number": "3", "track_artist_name": ""}, {"track_title": "Sunwheel (\u0421\u043e\u043d\u044f\u0447\u043d\u0435 \u041a\u043e\u043b\u043e)", "mood": {"1": {"TEXT": "Yearning", "ID": "65325"}, "2": {"TEXT": "Energetic Dreamy", "ID": "65341"}}, "tempo": {"1": {"TEXT": "Medium Tempo", "ID": "34283"}, "3": {"TEXT": "100s", "ID": "34320"}, "2": {"TEXT": "Medium Fast", "ID": "34291"}}, "track_gnid": "197593341-2281C7CA1955E6A82054EDEB1E2ACAD0", "track_number": "4", "track_artist_name": ""}, {"track_title": "Wind of the Night Forests (\u0412\u0456\u0442\u0435\u0440 \u041d\u0456\u0447\u043d\u0438\u0445 \u041b\u0456\u0441\u0456\u0432)", "mood": {"1": {"TEXT": "Brooding", "ID": "65329"}, "2": {"TEXT": "Alienated / Brooding", "ID": "43028"}}, "tempo": {"1": {"TEXT": "Medium Tempo", "ID": "34283"}, "3": {"TEXT": "100s", "ID": "34320"}, "2": {"TEXT": "Medium Fast", "ID": "34291"}}, "track_gnid": "197593342-9B730067C8E7AA8F82DBA48574316FB0", "track_number": "5", "track_artist_name": ""}, {"track_title": "The First Snow (\u041f\u0435\u0440\u0448\u0438\u0439 \u0421\u043d\u0456\u0433)", "mood": {"1": {"TEXT": "Yearning", "ID": "65325"}, "2": {"TEXT": "Energetic Dreamy", "ID": "65341"}}, "tempo": {"1": {"TEXT": "Medium Tempo", "ID": "34283"}, "3": {"TEXT": "100s", "ID": "34320"}, "2": {"TEXT": "Medium Fast", "ID": "34291"}}, "track_gnid": "197593343-8B96EC4AFAC459D7DBD690273D07364A", "track_number": "6", "track_artist_name": ""}], "xid": "", "album_gnid": "197593337-ED65E29732750336ED5B325F38E9B408", "artist_origin": {"1": {"TEXT": "Eastern Europe", "ID": "29897"}, "2": {"TEXT": "Ukraine", "ID": "30012"}}, "genre": {"1": {"TEXT": "Rock", "ID": "25313"}, "3": {"TEXT": "Black Metal", "ID": "25473"}, "2": {"TEXT": "Metal", "ID": "35478"}}, "album_title": "Autumn Aurora", "track_artist_name": "", "artist_type": {"1": {"TEXT": "Male", "ID": "29422"}, "2": {"TEXT": "Male Group", "ID": "29436"}}}